{
  "groups": [
    {
      "name": "yiji.yedis",
      "type": "com.global.boot.yedis.YedisProperties",
      "sourceType": "com.global.boot.yedis.YedisProperties"
    },
    {
      "name": "yiji.yedis.pool",
      "type": "com.global.boot.yedis.YedisProperties$Pool",
      "sourceType": "com.global.boot.yedis.YedisProperties"
    }
  ],
  "properties": [
    {
      "name": "yiji.yedis.enable",
      "type": "java.lang.Boolean",
      "sourceType": "com.global.boot.yedis.YedisProperties",
      "defaultValue": true
    },
    {
      "name": "yiji.yedis.expireTime",
      "type": "java.lang.Integer",
      "description": "可选：基于注解的Spring CacheManager，设置缓存的过期时间。默认为0，即不会过期\n 如果是使用RedisTemplate来显示读写缓存的，需要自己调用expire方法设置每个key的过期时间 单位秒",
      "sourceType": "com.global.boot.yedis.YedisProperties",
      "defaultValue": 0
    },
    {
      "name": "yiji.yedis.host",
      "type": "java.lang.String",
      "description": "必填：访问地址",
      "sourceType": "com.global.boot.yedis.YedisProperties",
      "defaultValue": "localhost"
    },
    {
      "name": "yiji.yedis.namespace",
      "type": "java.lang.String",
      "description": "可选：应用缓存空间名，必须注意，为避免与其它应用发生冲突，建议采用默认名，自定义命名空间一定要特别注意。",
      "sourceType": "com.global.boot.yedis.YedisProperties"
    },
    {
      "name": "yiji.yedis.pool.maxIdle",
      "type": "java.lang.Integer",
      "description": "最大空闲连接",
      "sourceType": "com.global.boot.yedis.YedisProperties$Pool",
      "defaultValue": 8
    },
    {
      "name": "yiji.yedis.pool.maxTotal",
      "type": "java.lang.Integer",
      "description": "最大连接数",
      "sourceType": "com.global.boot.yedis.YedisProperties$Pool",
      "defaultValue": 500
    },
    {
      "name": "yiji.yedis.pool.maxWait",
      "type": "java.lang.Integer",
      "description": "最大等待连接时间",
      "sourceType": "com.global.boot.yedis.YedisProperties$Pool",
      "defaultValue": 2000
    },
    {
      "name": "yiji.yedis.port",
      "type": "java.lang.Integer",
      "description": "必填：访问端口",
      "sourceType": "com.global.boot.yedis.YedisProperties",
      "defaultValue": 6379
    },
    {
      "name": "yiji.yedis.timeOut",
      "type": "java.lang.Integer",
      "description": "可选：创建socket连接的超时时间",
      "sourceType": "com.global.boot.yedis.YedisProperties",
      "defaultValue": 2000
    }
  ],
  "hints": []
}